porterminal/__init__.py
porterminal/__main__.py
porterminal/_version.py
porterminal/app.py
porterminal/asgi.py
porterminal/composition.py
porterminal/config.py
porterminal/container.py
porterminal/logging_setup.py
porterminal/updater.py
porterminal/application/__init__.py
porterminal/application/ports/__init__.py
porterminal/application/ports/connection_port.py
porterminal/application/ports/connection_registry_port.py
porterminal/application/services/__init__.py
porterminal/application/services/management_service.py
porterminal/application/services/session_service.py
porterminal/application/services/tab_service.py
porterminal/application/services/terminal_service.py
porterminal/cli/__init__.py
porterminal/cli/args.py
porterminal/cli/display.py
porterminal/cli/script_discovery.py
porterminal/domain/__init__.py
porterminal/domain/entities/__init__.py
porterminal/domain/entities/output_buffer.py
porterminal/domain/entities/session.py
porterminal/domain/entities/tab.py
porterminal/domain/ports/__init__.py
porterminal/domain/ports/pty_port.py
porterminal/domain/ports/session_repository.py
porterminal/domain/ports/tab_repository.py
porterminal/domain/services/__init__.py
porterminal/domain/services/environment_sanitizer.py
porterminal/domain/services/rate_limiter.py
porterminal/domain/services/session_limits.py
porterminal/domain/services/tab_limits.py
porterminal/domain/values/__init__.py
porterminal/domain/values/environment_rules.py
porterminal/domain/values/rate_limit_config.py
porterminal/domain/values/session_id.py
porterminal/domain/values/shell_command.py
porterminal/domain/values/tab_id.py
porterminal/domain/values/terminal_dimensions.py
porterminal/domain/values/user_id.py
porterminal/infrastructure/__init__.py
porterminal/infrastructure/auth.py
porterminal/infrastructure/cloudflared.py
porterminal/infrastructure/network.py
porterminal/infrastructure/server.py
porterminal/infrastructure/config/__init__.py
porterminal/infrastructure/config/config_service.py
ptn-0.6.2.dist-info/METADATA
ptn-0.6.2.dist-info/WHEEL
ptn-0.6.2.dist-info/entry_points.txt
ptn-0.6.2.dist-info/licenses/LICENSE
ptn-0.6.2.dist-info/RECORD
