Metadata-Version: 2.4
Name: ptn
Version: 0.6.2
Summary: Web-based terminal accessible from phone via Cloudflare Tunnel
Project-URL: Homepage, https://github.com/lyehe/porterminal
Project-URL: Repository, https://github.com/lyehe/porterminal
Project-URL: Documentation, https://github.com/lyehe/porterminal/tree/main/docs
Project-URL: Issues, https://github.com/lyehe/porterminal/issues
Author: Porterminal Contributors
Maintainer: Porterminal Contributors
License: AGPL-3.0-or-later
License-File: LICENSE
Keywords: cloudflare,mobile,pty,terminal,tunnel,web,websocket,xterm
Classifier: Development Status :: 4 - Beta
Classifier: Environment :: Web Environment
Classifier: Framework :: FastAPI
Classifier: Intended Audience :: Developers
Classifier: Intended Audience :: System Administrators
Classifier: License :: OSI Approved :: GNU Affero General Public License v3 or later (AGPLv3+)
Classifier: Operating System :: MacOS
Classifier: Operating System :: Microsoft :: Windows
Classifier: Operating System :: POSIX :: Linux
Classifier: Programming Language :: Python :: 3.12
Classifier: Programming Language :: Python :: 3.13
Classifier: Topic :: Internet :: WWW/HTTP
Classifier: Topic :: System :: Shells
Classifier: Topic :: Terminals :: Terminal Emulators/X Terminals
Requires-Python: >=3.12
Requires-Dist: bcrypt>=4.0.0
Requires-Dist: fastapi>=0.104.0
Requires-Dist: pydantic>=2.0
Requires-Dist: pywinpty>=2.0.0; sys_platform == 'win32'
Requires-Dist: pyyaml>=6.0
Requires-Dist: qrcode>=7.4
Requires-Dist: rich>=13.0
Requires-Dist: tyro>=0.9.0
Requires-Dist: uvicorn[standard]>=0.24.0
Provides-Extra: dev
Requires-Dist: watchfiles>=0.21.0; extra == 'dev'
